garfieldapi/__init__.py
garfieldapi-0.1.dist-info/LICENSE
garfieldapi-0.1.dist-info/METADATA
garfieldapi-0.1.dist-info/WHEEL
garfieldapi-0.1.dist-info/top_level.txt
garfieldapi-0.1.dist-info/RECORD
