Metadata-Version: 2.1
Name: garfieldapi
Version: 0.1
Summary: Fetch Garfield comics!
Home-page: https://github.com/themysticsavages/garfieldapi
Author: themysticsavages
Author-email: someemail@com.com
License: UNKNOWN
Platform: UNKNOWN
Classifier: Programming Language :: Python :: 3
Classifier: License :: OSI Approved :: MIT License
Classifier: Operating System :: OS Independent
Requires-Python: >=3.7
License-File: LICENSE
